headwai/__init__.py
headwai/headwai.py
headwai-0.1.1.dist-info/LICENSE
headwai-0.1.1.dist-info/METADATA
headwai-0.1.1.dist-info/WHEEL
headwai-0.1.1.dist-info/top_level.txt
headwai-0.1.1.dist-info/RECORD
